easynlp/__init__.py
easynlp/cli.py
easynlp/appzoo/__init__.py
easynlp/appzoo/api.py
easynlp/appzoo/application.py
easynlp/appzoo/dataset.py
easynlp/appzoo/data_augmentation/__init__.py
easynlp/appzoo/data_augmentation/model.py
easynlp/appzoo/data_augmentation/predictor.py
easynlp/appzoo/feature_vectorization/__init__.py
easynlp/appzoo/feature_vectorization/model.py
easynlp/appzoo/feature_vectorization/predictor.py
easynlp/appzoo/geep_classification/__init__.py
easynlp/appzoo/geep_classification/data.py
easynlp/appzoo/geep_classification/evaluator.py
easynlp/appzoo/geep_classification/model.py
easynlp/appzoo/geep_classification/predictor.py
easynlp/appzoo/language_modeling/__init__.py
easynlp/appzoo/language_modeling/data.py
easynlp/appzoo/language_modeling/evaluator.py
easynlp/appzoo/language_modeling/model.py
easynlp/appzoo/multi_modal/__init__.py
easynlp/appzoo/multi_modal/data.py
easynlp/appzoo/multi_modal/evaluator.py
easynlp/appzoo/multi_modal/model.py
easynlp/appzoo/multi_modal/predictor.py
easynlp/appzoo/sequence_classification/__init__.py
easynlp/appzoo/sequence_classification/data.py
easynlp/appzoo/sequence_classification/evaluator.py
easynlp/appzoo/sequence_classification/model.py
easynlp/appzoo/sequence_classification/predictor.py
easynlp/appzoo/sequence_labeling/__init__.py
easynlp/appzoo/sequence_labeling/data.py
easynlp/appzoo/sequence_labeling/evaluator.py
easynlp/appzoo/sequence_labeling/labeling_eval_utils.py
easynlp/appzoo/sequence_labeling/model.py
easynlp/appzoo/sequence_labeling/predictor.py
easynlp/appzoo/text2image_generation/__init__.py
easynlp/appzoo/text2image_generation/data.py
easynlp/appzoo/text2image_generation/evaluator.py
easynlp/appzoo/text2image_generation/model.py
easynlp/appzoo/text2image_generation/predictor.py
easynlp/appzoo/text2image_generation/vqgan.py
easynlp/appzoo/text_match/__init__.py
easynlp/appzoo/text_match/data.py
easynlp/appzoo/text_match/evaluator.py
easynlp/appzoo/text_match/model.py
pai_easynlp-0.0.3.dist-info/LICENSE
pai_easynlp-0.0.3.dist-info/METADATA
pai_easynlp-0.0.3.dist-info/NOTICE
pai_easynlp-0.0.3.dist-info/WHEEL
pai_easynlp-0.0.3.dist-info/entry_points.txt
pai_easynlp-0.0.3.dist-info/top_level.txt
pai_easynlp-0.0.3.dist-info/RECORD
