Metadata-Version: 2.1
Name: pai-easynlp
Version: 0.0.3
Summary: PAI EasyNLP Toolkit
Home-page: https://github.com/alibaba/EasyNLP
Author: PAI NLP
Author-email: easynlp@list.alibaba-inc.com
License: Apache-2.0
Platform: UNKNOWN
Requires-Python: >=2.7,>=3.6
License-File: LICENSE
License-File: NOTICE
Requires-Dist: bs4
Requires-Dist: filelock
Requires-Dist: importlib-metadata (==4.5)
Requires-Dist: jieba
Requires-Dist: numpy
Requires-Dist: packaging
Requires-Dist: regex
Requires-Dist: sacremoses
Requires-Dist: scikit-learn
Requires-Dist: scipy (>=1.5.4)
Requires-Dist: sentencepiece
Requires-Dist: tensorboard
Requires-Dist: tokenizers (==0.10.1)
Requires-Dist: torch (<1.10,>=1.8.0)
Requires-Dist: rouge
Requires-Dist: tqdm
Requires-Dist: pillow
